{"PageTitle":"Biệt thự Villa Park 8x17m cơ bản 18tr/th - 10x17m full 24tr/th nhà mới - khu compound an ninh 24/7 - Tìm Nhà Đất - Kênh nhà đất số 1 Việt Nam","Url":"file:/Users/batuan/Documents/hoctap/datn/vips_java/databatdongsan/website/timnhadat/timnhadat19.htm","WindowWidth":"1420","WindowHeight":"980","PageRectTop":"0","PageRectLeft":"0","PageRectWidth":"1420","PageRectHeight":"980","neworder":"0","order":"0"}
{"DoC":"5","FontSize_O":11.0,"FontSize_R":1.0,"FontWeight":"700","FontWeight_O":700.0,"FontWeight_R":1.0,"InnerTextLength_O":45.0,"InnerTextLength_R":0.014841688654353561,"ImgNum_O":6.0,"ImgNum_R":0.3,"ImgSize":0.02241108831692727,"IsImg":"false","LinkNum_O":12.0,"LinkNum_R":0.14634146341463414,"LinkTextLength_O":0.026981450252951095,"LinkTextLength_R":0.026981450252951095,"InteractionNum_O":0.0,"InteractionNum_R":0.0,"InteractionSize_O":0.0,"InteractionSize_R":0.0,"FormNum_O":12.0,"FormNum_R":0.14634146341463414,"FormSize_O":1.0,"FormSize_R":1.0,"OptionNum_O":0.0,"OptionNum_R":0.0,"OptionTextLength_O":0.0,"OptionTextLength_R":0.0,"TableNum_O":0.0,"TableNum_R":0.0,"ParaNum_O":1.0,"ParaNum_R":0.05,"InnerHtmlLength_O":1695.0,"InnerHtmlLength_R":0.008122484186313974,"BlockCenterX":0.5,"BlockCenterY":0.2663622526636225,"BlockRectWidth":1.0,"BlockRectHeight":0.14285714285714285,"ContainTable":"false","TextLen":"45","DOMCldNum":"7","BgColor":"#ffffff","ObjectRectLeft":"0","ObjectRectTop":"0","ObjectRectWidth":"1420","ObjectRectHeight":"140","ID":"1-1","order":"2","FrameSourceIndex":"0","SourceIndex":"148;141;160;154","Content":"Kênh nhà đất số 1 Việt Nam    Đăng ký Đăng nhập  ","xPath":"/html[1]/body[1]/div[1]/div[2]/div[1]/div[1]","XContent":"/html[1]/body[1]/div[1]/div[2]/div[1]/div[1]/p[1](+)/html[1]/body[1]/div[1]/div[2]/div[1]/div[1](+)/html[1]/body[1]/div[1]/div[2]/div[1]/div[2]/div[2](+)/html[1]/body[1]/div[1]/div[2]/div[1]/div[2]/div[1](+)","AllClassName":"slg pc, logo float-left, header-actions, header-banner, ","label":"0"}
{"DoC":"5","FontSize_O":12.0,"FontSize_R":1.0909090909090908,"FontWeight":"700","FontWeight_O":700.0,"FontWeight_R":1.0,"InnerTextLength_O":81.0,"InnerTextLength_R":0.02671503957783641,"ImgNum_O":1.0,"ImgNum_R":0.05,"ImgSize":3.66622419133323E-4,"IsImg":"false","LinkNum_O":12.0,"LinkNum_R":0.14634146341463414,"LinkTextLength_O":0.13490725126475547,"LinkTextLength_R":0.13490725126475547,"InteractionNum_O":0.0,"InteractionNum_R":0.0,"InteractionSize_O":0.0,"InteractionSize_R":0.0,"FormNum_O":12.0,"FormNum_R":0.14634146341463414,"FormSize_O":1.0909090909090908,"FormSize_R":1.0909090909090908,"OptionNum_O":0.0,"OptionNum_R":0.0,"OptionTextLength_O":0.0,"OptionTextLength_R":0.0,"TableNum_O":0.0,"TableNum_R":0.0,"ParaNum_O":0.0,"ParaNum_R":0.0,"InnerHtmlLength_O":10172.0,"InnerHtmlLength_R":0.04874448917002108,"BlockCenterX":0.5,"BlockCenterY":0.5,"BlockRectWidth":1.0,"BlockRectHeight":0.030612244897959183,"ContainTable":"false","TextLen":"81","DOMCldNum":"13","BgColor":"#055699","ObjectRectLeft":"0","ObjectRectTop":"145","ObjectRectWidth":"1420","ObjectRectHeight":"30","ID":"1-2","order":"3","FrameSourceIndex":"0","SourceIndex":"183","Content":"Nhà đất bánNhà đất cho thuêNhà đất cần muaNhà đất cần thuêKhuyến mãi - Thông báo  ","xPath":"/html[1]/body[1]/div[1]/div[2]/div[2]","XContent":"/html[1]/body[1]/div[1]/div[2]/div[2](+)","AllClassName":"menu, ","label":"0"}
{"DoC":"5","FontSize_O":12.0,"FontSize_R":1.0909090909090908,"FontWeight":"400","FontWeight_O":400.0,"FontWeight_R":0.5714285714285714,"InnerTextLength_O":26.0,"InnerTextLength_R":0.008575197889182058,"ImgNum_O":0.0,"ImgNum_R":0.0,"ImgSize":0.0,"IsImg":"false","LinkNum_O":0.0,"LinkNum_R":0.0,"LinkTextLength_O":0.0,"LinkTextLength_R":0.0,"InteractionNum_O":0.0,"InteractionNum_R":0.0,"InteractionSize_O":0.0,"InteractionSize_R":0.0,"FormNum_O":0.0,"FormNum_R":0.0,"FormSize_O":1.0909090909090908,"FormSize_R":1.0909090909090908,"OptionNum_O":0.0,"OptionNum_R":0.0,"OptionTextLength_O":0.0,"OptionTextLength_R":0.0,"TableNum_O":0.0,"TableNum_R":0.0,"ParaNum_O":0.0,"ParaNum_R":0.0,"InnerHtmlLength_O":1399.0,"InnerHtmlLength_R":0.006704044470001917,"BlockCenterX":0.5,"BlockCenterY":0.5,"BlockRectWidth":1.0,"BlockRectHeight":0.02857142857142857,"ContainTable":"false","TextLen":"26","DOMCldNum":"13","BgColor":"#ffffff","ObjectRectLeft":"0","ObjectRectTop":"185","ObjectRectWidth":"1420","ObjectRectHeight":"28","ID":"1-3","order":"4","FrameSourceIndex":"0","SourceIndex":"502","Content":" Nhà đất cho thuê Tìm kiếm ","xPath":"/html[1]/body[1]/div[1]/div[2]/div[3]","XContent":"/html[1]/body[1]/div[1]/div[2]/div[3](+)","AllClassName":"menu-search, ","label":"0"}
{"DoC":"10","FontSize_O":16.0,"FontSize_R":1.4545454545454546,"FontWeight":"700","FontWeight_O":700.0,"FontWeight_R":1.0,"InnerTextLength_O":97.0,"InnerTextLength_R":0.03199208443271768,"ImgNum_O":0.0,"ImgNum_R":0.0,"ImgSize":0.0,"IsImg":"false","LinkNum_O":0.0,"LinkNum_R":0.0,"LinkTextLength_O":0.0,"LinkTextLength_R":0.0,"InteractionNum_O":0.0,"InteractionNum_R":0.0,"InteractionSize_O":0.0,"InteractionSize_R":0.0,"FormNum_O":0.0,"FormNum_R":0.0,"FormSize_O":1.4545454545454546,"FormSize_R":1.4545454545454546,"OptionNum_O":0.0,"OptionNum_R":0.0,"OptionTextLength_O":0.0,"OptionTextLength_R":0.0,"TableNum_O":0.0,"TableNum_R":0.0,"ParaNum_O":0.0,"ParaNum_R":0.0,"InnerHtmlLength_O":164.0,"InnerHtmlLength_R":7.858922752539773E-4,"BlockCenterX":0.3274647887323944,"BlockCenterY":0.5,"BlockRectWidth":0.6549295774647887,"BlockRectHeight":0.05510204081632653,"ContainTable":"false","TextLen":"97","DOMCldNum":"23","BgColor":"#ffffff","ObjectRectLeft":"0","ObjectRectTop":"218","ObjectRectWidth":"930","ObjectRectHeight":"54","ID":"1-4-1-1","order":"5","FrameSourceIndex":"0","SourceIndex":"2708","Content":"Biệt thự Villa Park 8x17m cơ bản 18tr/th - 10x17m full 24tr/th nhà mới - khu compoundan ninh 24/7 ","xPath":"/html[1]/body[1]/div[1]/div[2]/div[4]/div[2]/div[1]/h1[1]","XContent":"/html[1]/body[1]/div[1]/div[2]/div[4]/div[2]/div[1]/h1[1](+)","AllClassName":"post-title, ","label":"1"}
{"DoC":"5","FontSize_O":12.0,"FontSize_R":1.0909090909090908,"FontWeight":"normal","FontWeight_O":400.0,"FontWeight_R":0.5714285714285714,"InnerTextLength_O":61.0,"InnerTextLength_R":0.020118733509234828,"ImgNum_O":0.0,"ImgNum_R":0.0,"ImgSize":0.0,"IsImg":"false","LinkNum_O":0.0,"LinkNum_R":0.0,"LinkTextLength_O":0.0,"LinkTextLength_R":0.0,"InteractionNum_O":0.0,"InteractionNum_R":0.0,"InteractionSize_O":0.0,"InteractionSize_R":0.0,"FormNum_O":0.0,"FormNum_R":0.0,"FormSize_O":1.0909090909090908,"FormSize_R":1.0909090909090908,"OptionNum_O":0.0,"OptionNum_R":0.0,"OptionTextLength_O":0.0,"OptionTextLength_R":0.0,"TableNum_O":0.0,"TableNum_R":0.0,"ParaNum_O":0.0,"ParaNum_R":0.0,"InnerHtmlLength_O":420.0,"InnerHtmlLength_R":0.0020126509488211618,"BlockCenterX":0.3274647887323944,"BlockCenterY":0.5,"BlockRectWidth":0.6549295774647887,"BlockRectHeight":0.04081632653061224,"ContainTable":"false","TextLen":"61","DOMCldNum":"23","BgColor":"#ffffff","ObjectRectLeft":"0","ObjectRectTop":"282","ObjectRectWidth":"930","ObjectRectHeight":"40","ID":"1-4-1-2","order":"6","FrameSourceIndex":"0","SourceIndex":"2711;2718;2726","Content":"Khu vực: Quận 9, Hồ Chí Minh Giá: Thương lượng Diện tích: 136m² ","xPath":"/html[1]/body[1]/div[1]/div[2]/div[4]/div[2]/div[1]/div[1]","XContent":"/html[1]/body[1]/div[1]/div[2]/div[4]/div[2]/div[1]/div[1](+)/html[1]/body[1]/div[1]/div[2]/div[4]/div[2]/div[1]/div[2](+)/html[1]/body[1]/div[1]/div[2]/div[4]/div[2]/div[1]/div[3](+)","AllClassName":"post-location, post-price, post-area, ","label":"1"}
{"DoC":"10","FontSize_O":12.0,"FontSize_R":1.0909090909090908,"FontWeight":"700","FontWeight_O":700.0,"FontWeight_R":1.0,"InnerTextLength_O":15.0,"InnerTextLength_R":0.004947229551451188,"ImgNum_O":0.0,"ImgNum_R":0.0,"ImgSize":0.0,"IsImg":"false","LinkNum_O":0.0,"LinkNum_R":0.0,"LinkTextLength_O":0.0,"LinkTextLength_R":0.0,"InteractionNum_O":0.0,"InteractionNum_R":0.0,"InteractionSize_O":0.0,"InteractionSize_R":0.0,"FormNum_O":0.0,"FormNum_R":0.0,"FormSize_O":1.0909090909090908,"FormSize_R":1.0909090909090908,"OptionNum_O":0.0,"OptionNum_R":0.0,"OptionTextLength_O":0.0,"OptionTextLength_R":0.0,"TableNum_O":0.0,"TableNum_R":0.0,"ParaNum_O":0.0,"ParaNum_R":0.0,"InnerHtmlLength_O":111.0,"InnerHtmlLength_R":5.319148936170213E-4,"BlockCenterX":0.3274647887323944,"BlockCenterY":0.5,"BlockRectWidth":0.6549295774647887,"BlockRectHeight":0.018367346938775512,"ContainTable":"false","TextLen":"15","DOMCldNum":"7","BgColor":"#ffffff","ObjectRectLeft":"0","ObjectRectTop":"332","ObjectRectWidth":"930","ObjectRectHeight":"18","ID":"1-4-1-3","order":"7","FrameSourceIndex":"0","SourceIndex":"2737","Content":"Thông tin mô tả ","xPath":"/html[1]/body[1]/div[1]/div[2]/div[4]/div[2]/div[1]/div[5]/div[1]","XContent":"/html[1]/body[1]/div[1]/div[2]/div[4]/div[2]/div[1]/div[5]/div[1](+)","AllClassName":"post-detail-title, ","label":"1"}
{"DoC":"8","FontSize_O":14.0,"FontSize_R":1.2727272727272727,"FontWeight":"normal","FontWeight_O":400.0,"FontWeight_R":0.5714285714285714,"InnerTextLength_O":1033.0,"InnerTextLength_R":0.3406992084432718,"ImgNum_O":0.0,"ImgNum_R":0.0,"ImgSize":0.0,"IsImg":"false","LinkNum_O":0.0,"LinkNum_R":0.0,"LinkTextLength_O":0.0,"LinkTextLength_R":0.0,"InteractionNum_O":0.0,"InteractionNum_R":0.0,"InteractionSize_O":0.0,"InteractionSize_R":0.0,"FormNum_O":0.0,"FormNum_R":0.0,"FormSize_O":1.2727272727272727,"FormSize_R":1.2727272727272727,"OptionNum_O":0.0,"OptionNum_R":0.0,"OptionTextLength_O":0.0,"OptionTextLength_R":0.0,"TableNum_O":0.0,"TableNum_R":0.0,"ParaNum_O":19.0,"ParaNum_R":0.95,"InnerHtmlLength_O":1257.0,"InnerHtmlLength_R":0.006023576768257619,"BlockCenterX":0.3274647887323944,"BlockCenterY":0.5,"BlockRectWidth":0.6549295774647887,"BlockRectHeight":0.7040816326530612,"ContainTable":"false","TextLen":"1033","DOMCldNum":"7","BgColor":"#ffffff","ObjectRectLeft":"0","ObjectRectTop":"355","ObjectRectWidth":"930","ObjectRectHeight":"690","ID":"1-4-1-4","order":"8","FrameSourceIndex":"0","SourceIndex":"2740","Content":"Cho thuê biệt thự nguyên căn khu biệt lập Villa Park, Quận 9.- Nhà mới đầy đủ tiện nghi dọn vào ở ngay.- Diện tích sử dụng: 250m2, gồm 1 trệt và 3 lầu.+ Có 4 phòng ngủ, 5 toilet, 1 phòng sinh hoạt chung, 1 sân trước và 1 sân sau, có balcony.+ Thiết kế đẹp, nội thất cao cấp: Trang bị đầy đủ với tủ, giường, nệm, Drap Satin lụa, ghế sofa, bàn ăn, bếp có máyhút mùi... Có cửa sổ, ban công.+ Gần trường học, bệnh viện, trung tâm mua sắm, cửa hàng tiện lợi 24/24.+ Hồ cảnh quan, khu vui chơi trẻ em, công viên cây xanh và lối đi bộ rộng lớn.+ Hồ bơi, phòng tập gym không tính phí,...+ An ninh kiểm soát nghiêm, camera toàn khu, bảo vệ 24/7.- Dân trí cao, công viên và khuôn viên rộng lớn môi trường trong lành thích hợp để ở cũng như nghỉ dưỡng xa khói bụithành phố.+ Nằm ngay vị trí đắc địa, dễ dàng di chuyển vào trung tâm Quận 1, Quận 2 và Quận 7, đồng thời rất gần với ĐồngNai và Vũng Tàu theo hướng Vành Đai đường cao.* Giá cho thuê:+ Nhà cơ bản 18tr/th.+ Nhà full nội thất 24 - 25tr/th.Liên hệ Duy để xem nhà 0908 96 97 95 anh Duy. ","xPath":"/html[1]/body[1]/div[1]/div[2]/div[4]/div[2]/div[1]/div[5]/div[2]","XContent":"/html[1]/body[1]/div[1]/div[2]/div[4]/div[2]/div[1]/div[5]/div[2](+)","AllClassName":"post-detail-content, ","label":"1"}
{"DoC":"5","FontSize_O":12.0,"FontSize_R":1.0909090909090908,"FontWeight":"normal","FontWeight_O":400.0,"FontWeight_R":0.5714285714285714,"InnerTextLength_O":39.0,"InnerTextLength_R":0.012862796833773086,"ImgNum_O":1.0,"ImgNum_R":0.05,"ImgSize":2.094574792697433E-4,"IsImg":"false","LinkNum_O":2.0,"LinkNum_R":0.024390243902439025,"LinkTextLength_O":0.011804384485666104,"LinkTextLength_R":0.011804384485666104,"InteractionNum_O":0.0,"InteractionNum_R":0.0,"InteractionSize_O":0.0,"InteractionSize_R":0.0,"FormNum_O":2.0,"FormNum_R":0.024390243902439025,"FormSize_O":1.0909090909090908,"FormSize_R":1.0909090909090908,"OptionNum_O":0.0,"OptionNum_R":0.0,"OptionTextLength_O":0.0,"OptionTextLength_R":0.0,"TableNum_O":0.0,"TableNum_R":0.0,"ParaNum_O":0.0,"ParaNum_R":0.0,"InnerHtmlLength_O":1016.0,"InnerHtmlLength_R":0.0048686984857197625,"BlockCenterX":0.8338028169014085,"BlockCenterY":0.5,"BlockRectWidth":0.3323943661971831,"BlockRectHeight":0.0673469387755102,"ContainTable":"false","TextLen":"39","DOMCldNum":"5","BgColor":"#ffffff","ObjectRectLeft":"948","ObjectRectTop":"218","ObjectRectWidth":"472","ObjectRectHeight":"66","ID":"1-4-2-1","order":"9","FrameSourceIndex":"0","SourceIndex":"540","Content":"Nhận bản tin từ Timnhadat.net.vnĐăng ký ","xPath":"/html[1]/body[1]/div[1]/div[2]/div[4]/div[1]/div[1]","XContent":"/html[1]/body[1]/div[1]/div[2]/div[4]/div[1]/div[1](+)","AllClassName":"newsletter-form-small, ","label":"0"}
{"DoC":"5","FontSize_O":12.0,"FontSize_R":1.0909090909090908,"FontWeight":"700","FontWeight_O":700.0,"FontWeight_R":1.0,"InnerTextLength_O":61.0,"InnerTextLength_R":0.020118733509234828,"ImgNum_O":0.0,"ImgNum_R":0.0,"ImgSize":0.0,"IsImg":"false","LinkNum_O":0.0,"LinkNum_R":0.0,"LinkTextLength_O":0.0,"LinkTextLength_R":0.0,"InteractionNum_O":0.0,"InteractionNum_R":0.0,"InteractionSize_O":0.0,"InteractionSize_R":0.0,"FormNum_O":0.0,"FormNum_R":0.0,"FormSize_O":1.0909090909090908,"FormSize_R":1.0909090909090908,"OptionNum_O":0.0,"OptionNum_R":0.0,"OptionTextLength_O":0.0,"OptionTextLength_R":0.0,"TableNum_O":0.0,"TableNum_R":0.0,"ParaNum_O":0.0,"ParaNum_R":0.0,"InnerHtmlLength_O":814.0,"InnerHtmlLength_R":0.003900709219858156,"BlockCenterX":0.8338028169014085,"BlockCenterY":0.5,"BlockRectWidth":0.3323943661971831,"BlockRectHeight":0.07857142857142857,"ContainTable":"false","TextLen":"61","DOMCldNum":"5","BgColor":"#055699","ObjectRectLeft":"948","ObjectRectTop":"302","ObjectRectWidth":"472","ObjectRectHeight":"77","ID":"1-4-2-2-1","order":"10","FrameSourceIndex":"0","SourceIndex":"570;578","Content":"Tìm kiếm trên 10.000.000 tin rao Nhà đất bánNhà đất cho thuê ","xPath":"/html[1]/body[1]/div[1]/div[2]/div[4]/div[1]/div[2]/div[1]","XContent":"/html[1]/body[1]/div[1]/div[2]/div[4]/div[1]/div[2]/div[1](+)/html[1]/body[1]/div[1]/div[2]/div[4]/div[1]/div[2]/div[2]/div[1](+)","AllClassName":"block-title, tabs, ","label":"0"}
{"DoC":"8","FontSize_O":12.0,"FontSize_R":1.0909090909090908,"FontWeight":"normal","FontWeight_O":400.0,"FontWeight_R":0.5714285714285714,"InnerTextLength_O":96.0,"InnerTextLength_R":0.0316622691292876,"ImgNum_O":0.0,"ImgNum_R":0.0,"ImgSize":0.0,"IsImg":"false","LinkNum_O":0.0,"LinkNum_R":0.0,"LinkTextLength_O":0.0,"LinkTextLength_R":0.0,"InteractionNum_O":0.0,"InteractionNum_R":0.0,"InteractionSize_O":0.0,"InteractionSize_R":0.0,"FormNum_O":0.0,"FormNum_R":0.0,"FormSize_O":1.0909090909090908,"FormSize_R":1.0909090909090908,"OptionNum_O":0.0,"OptionNum_R":0.0,"OptionTextLength_O":0.0,"OptionTextLength_R":0.0,"TableNum_O":0.0,"TableNum_R":0.0,"ParaNum_O":0.0,"ParaNum_R":0.0,"InnerHtmlLength_O":83038.0,"InnerHtmlLength_R":0.3979202606862181,"BlockCenterX":0.8338028169014085,"BlockCenterY":0.5,"BlockRectWidth":0.3323943661971831,"BlockRectHeight":0.39387755102040817,"ContainTable":"false","TextLen":"96","DOMCldNum":"3","BgColor":"#ffffff","ObjectRectLeft":"948","ObjectRectTop":"389","ObjectRectWidth":"472","ObjectRectHeight":"386","ID":"1-4-2-2-2","order":"11","FrameSourceIndex":"0","SourceIndex":"597","Content":"- Cho thuê nhà riêngHồ Chí MinhQuận 9100 - 150m²< 500 triệuPhường Phú Hữu--Chọn Đường/Phố--4+KXĐ ","xPath":"/html[1]/body[1]/div[1]/div[2]/div[4]/div[1]/div[2]/div[2]/form[1]/div[1]/div[1]","XContent":"/html[1]/body[1]/div[1]/div[2]/div[4]/div[1]/div[2]/div[2]/form[1]/div[1]/div[1](+)","AllClassName":"tab-content active, ","label":"0"}
{"DoC":"5","FontSize_O":12.0,"FontSize_R":1.0909090909090908,"FontWeight":"normal","FontWeight_O":400.0,"FontWeight_R":0.5714285714285714,"InnerTextLength_O":26.0,"InnerTextLength_R":0.008575197889182058,"ImgNum_O":0.0,"ImgNum_R":0.0,"ImgSize":0.0,"IsImg":"false","LinkNum_O":2.0,"LinkNum_R":0.024390243902439025,"LinkTextLength_O":0.026981450252951095,"LinkTextLength_R":0.026981450252951095,"InteractionNum_O":0.0,"InteractionNum_R":0.0,"InteractionSize_O":0.0,"InteractionSize_R":0.0,"FormNum_O":2.0,"FormNum_R":0.024390243902439025,"FormSize_O":1.0909090909090908,"FormSize_R":1.0909090909090908,"OptionNum_O":0.0,"OptionNum_R":0.0,"OptionTextLength_O":0.0,"OptionTextLength_R":0.0,"TableNum_O":0.0,"TableNum_R":0.0,"ParaNum_O":0.0,"ParaNum_R":0.0,"InnerHtmlLength_O":608.0,"InnerHtmlLength_R":0.0029135518497220626,"BlockCenterX":0.8338028169014085,"BlockCenterY":0.5,"BlockRectWidth":0.3323943661971831,"BlockRectHeight":0.25510204081632654,"ContainTable":"false","TextLen":"26","DOMCldNum":"5","BgColor":"#ffffff","ObjectRectLeft":"948","ObjectRectTop":"795","ObjectRectWidth":"472","ObjectRectHeight":"250","ID":"1-4-2-2-3","order":"12","FrameSourceIndex":"0","SourceIndex":"2681","Content":"Ẩn tìm nâng cao  Tìm kiếm ","xPath":"/html[1]/body[1]/div[1]/div[2]/div[4]/div[1]/div[2]/div[2]/form[1]/div[2]","XContent":"/html[1]/body[1]/div[1]/div[2]/div[4]/div[1]/div[2]/div[2]/form[1]/div[2](+)","AllClassName":"actions, ","label":"0"}
{"DoC":"10","FontSize_O":12.0,"FontSize_R":1.0909090909090908,"FontWeight":"700","FontWeight_O":700.0,"FontWeight_R":1.0,"InnerTextLength_O":19.0,"InnerTextLength_R":0.006266490765171504,"ImgNum_O":0.0,"ImgNum_R":0.0,"ImgSize":0.0,"IsImg":"false","LinkNum_O":0.0,"LinkNum_R":0.0,"LinkTextLength_O":0.0,"LinkTextLength_R":0.0,"InteractionNum_O":0.0,"InteractionNum_R":0.0,"InteractionSize_O":0.0,"InteractionSize_R":0.0,"FormNum_O":0.0,"FormNum_R":0.0,"FormSize_O":1.0909090909090908,"FormSize_R":1.0909090909090908,"OptionNum_O":0.0,"OptionNum_R":0.0,"OptionTextLength_O":0.0,"OptionTextLength_R":0.0,"TableNum_O":0.0,"TableNum_R":0.0,"ParaNum_O":0.0,"ParaNum_R":0.0,"InnerHtmlLength_O":109.0,"InnerHtmlLength_R":5.223308414797777E-4,"BlockCenterX":0.5,"BlockCenterY":0.5,"BlockRectWidth":1.0,"BlockRectHeight":0.018367346938775512,"ContainTable":"false","TextLen":"19","DOMCldNum":"7","BgColor":"#ffffff","ObjectRectLeft":"0","ObjectRectTop":"1055","ObjectRectWidth":"1420","ObjectRectHeight":"18","ID":"1-5","order":"13","FrameSourceIndex":"0","SourceIndex":"2781","Content":"(batdongsan.com.vn) ","xPath":"/html[1]/body[1]/div[1]/div[2]/div[4]/div[2]/div[1]/div[5]/div[3]","XContent":"/html[1]/body[1]/div[1]/div[2]/div[4]/div[2]/div[1]/div[5]/div[3](+)","AllClassName":"post-source, ","label":"1"}
{"DoC":"10","FontSize_O":12.0,"FontSize_R":1.0909090909090908,"FontWeight":"700","FontWeight_O":700.0,"FontWeight_R":1.0,"InnerTextLength_O":7.0,"InnerTextLength_R":0.002308707124010554,"ImgNum_O":0.0,"ImgNum_R":0.0,"ImgSize":0.0,"IsImg":"false","LinkNum_O":0.0,"LinkNum_R":0.0,"LinkTextLength_O":0.0,"LinkTextLength_R":0.0,"InteractionNum_O":0.0,"InteractionNum_R":0.0,"InteractionSize_O":0.0,"InteractionSize_R":0.0,"FormNum_O":0.0,"FormNum_R":0.0,"FormSize_O":1.0909090909090908,"FormSize_R":1.0909090909090908,"OptionNum_O":0.0,"OptionNum_R":0.0,"OptionTextLength_O":0.0,"OptionTextLength_R":0.0,"TableNum_O":0.0,"TableNum_R":0.0,"ParaNum_O":0.0,"ParaNum_R":0.0,"InnerHtmlLength_O":130.0,"InnerHtmlLength_R":6.229633889208358E-4,"BlockCenterX":0.5,"BlockCenterY":0.5,"BlockRectWidth":1.0,"BlockRectHeight":0.018367346938775512,"ContainTable":"false","TextLen":"7","DOMCldNum":"7","BgColor":"#055699","ObjectRectLeft":"0","ObjectRectTop":"1099","ObjectRectWidth":"1420","ObjectRectHeight":"18","ID":"1-6","order":"14","FrameSourceIndex":"0","SourceIndex":"2787","Content":"XEM ẢNH ","xPath":"/html[1]/body[1]/div[1]/div[2]/div[4]/div[2]/div[1]/div[6]/div[1]","XContent":"/html[1]/body[1]/div[1]/div[2]/div[4]/div[2]/div[1]/div[6]/div[1](+)","AllClassName":"block-title active, ","label":"1"}
{"DoC":"8","FontSize_O":12.0,"FontSize_R":1.0909090909090908,"FontWeight":"normal","FontWeight_O":400.0,"FontWeight_R":0.5714285714285714,"InnerTextLength_O":0.0,"InnerTextLength_R":0.0,"ImgNum_O":8.0,"ImgNum_R":0.4,"ImgSize":0.10801799782784836,"IsImg":"false","LinkNum_O":0.0,"LinkNum_R":0.0,"LinkTextLength_O":0.0,"LinkTextLength_R":0.0,"InteractionNum_O":0.0,"InteractionNum_R":0.0,"InteractionSize_O":0.0,"InteractionSize_R":0.0,"FormNum_O":0.0,"FormNum_R":0.0,"FormSize_O":1.0909090909090908,"FormSize_R":1.0909090909090908,"OptionNum_O":0.0,"OptionNum_R":0.0,"OptionTextLength_O":0.0,"OptionTextLength_R":0.0,"TableNum_O":0.0,"TableNum_R":0.0,"ParaNum_O":0.0,"ParaNum_R":0.0,"InnerHtmlLength_O":3386.0,"InnerHtmlLength_R":0.01622580026835346,"BlockCenterX":0.5,"BlockCenterY":0.5,"BlockRectWidth":1.0,"BlockRectHeight":0.6377551020408163,"ContainTable":"false","TextLen":"0","DOMCldNum":"1","BgColor":"#ffffff","ObjectRectLeft":"0","ObjectRectTop":"1132","ObjectRectWidth":"1420","ObjectRectHeight":"625","ID":"1-7","order":"15","FrameSourceIndex":"0","SourceIndex":"8461;2808","Content":"  ","xPath":"/html[1]/body[1]/div[1]/div[2]/div[4]/div[2]/div[1]/div[6]/div[3]/div[2]/div[1]/div[2]","XContent":"/html[1]/body[1]/div[1]/div[2]/div[4]/div[2]/div[1]/div[6]/div[3]/div[2]/div[1]/div[1]/div[1]/div[1]/img[1](+)/html[1]/body[1]/div[1]/div[2]/div[4]/div[2]/div[1]/div[6]/div[3]/div[2]/div[1]/div[2](+)","AllClassName":"fotorama__img, fotorama__nav-wrap, ","label":"1"}
{"DoC":"8","FontSize_O":12.0,"FontSize_R":1.0909090909090908,"FontWeight":"normal","FontWeight_O":400.0,"FontWeight_R":0.5714285714285714,"InnerTextLength_O":171.0,"InnerTextLength_R":0.05639841688654353,"ImgNum_O":0.0,"ImgNum_R":0.0,"ImgSize":0.0,"IsImg":"false","LinkNum_O":0.0,"LinkNum_R":0.0,"LinkTextLength_O":0.0,"LinkTextLength_R":0.0,"InteractionNum_O":0.0,"InteractionNum_R":0.0,"InteractionSize_O":0.0,"InteractionSize_R":0.0,"FormNum_O":0.0,"FormNum_R":0.0,"FormSize_O":1.0909090909090908,"FormSize_R":1.0909090909090908,"OptionNum_O":0.0,"OptionNum_R":0.0,"OptionTextLength_O":1.0,"OptionTextLength_R":0.5,"TableNum_O":0.0,"TableNum_R":0.0,"ParaNum_O":0.0,"ParaNum_R":0.0,"InnerHtmlLength_O":2041.0,"InnerHtmlLength_R":0.009780525206057121,"BlockCenterX":0.22570422535211268,"BlockCenterY":0.5,"BlockRectWidth":0.45140845070422536,"BlockRectHeight":0.19591836734693877,"ContainTable":"true","TextLen":"171","DOMCldNum":"0","BgColor":"#ffffff","ObjectRectLeft":"0","ObjectRectTop":"1778","ObjectRectWidth":"641","ObjectRectHeight":"192","ID":"1-8-1","order":"16","FrameSourceIndex":"0","SourceIndex":"2839","Content":"Đặc điểm bất động sảnLoại tin raoCho thuê nhà riêngĐịa chỉDự án Villa Park, Đường Bưng Ông Thoàn, PhườngPhú Hữu, Quận 9, Hồ Chí MinhSố phòng ngủ4(Phòng)Số toilet5Nội thất5 ","xPath":"/html[1]/body[1]/div[1]/div[2]/div[4]/div[2]/div[1]/div[7]/div[1]","XContent":"/html[1]/body[1]/div[1]/div[2]/div[4]/div[2]/div[1]/div[7]/div[1](+)","AllClassName":"div-table left, ","label":"1"}
{"DoC":"5","FontSize_O":12.0,"FontSize_R":1.0909090909090908,"FontWeight":"normal","FontWeight_O":400.0,"FontWeight_R":0.5714285714285714,"InnerTextLength_O":139.0,"InnerTextLength_R":0.045844327176781004,"ImgNum_O":0.0,"ImgNum_R":0.0,"ImgSize":0.0,"IsImg":"false","LinkNum_O":0.0,"LinkNum_R":0.0,"LinkTextLength_O":0.0,"LinkTextLength_R":0.0,"InteractionNum_O":0.0,"InteractionNum_R":0.0,"InteractionSize_O":0.0,"InteractionSize_R":0.0,"FormNum_O":0.0,"FormNum_R":0.0,"FormSize_O":1.0909090909090908,"FormSize_R":1.0909090909090908,"OptionNum_O":0.0,"OptionNum_R":0.0,"OptionTextLength_O":1.0,"OptionTextLength_R":0.5,"TableNum_O":0.0,"TableNum_R":0.0,"ParaNum_O":0.0,"ParaNum_R":0.0,"InnerHtmlLength_O":1706.0,"InnerHtmlLength_R":0.008175196473068814,"BlockCenterX":0.7299295774647887,"BlockCenterY":0.5,"BlockRectWidth":0.5401408450704225,"BlockRectHeight":0.19591836734693877,"ContainTable":"true","TextLen":"139","DOMCldNum":"0","BgColor":"#ffffff","ObjectRectLeft":"653","ObjectRectTop":"1778","ObjectRectWidth":"767","ObjectRectHeight":"192","ID":"1-8-2","order":"17","FrameSourceIndex":"0","SourceIndex":"2902","Content":"Liên hệTên liên hệTrương Khánh DuyĐịa chỉVõ Văn Kiệt, Cầu Ông Lãnh, Quận1, Hồ Chí Minh, Việt NamDi động0917998992Emailarisduy4648@gmail.com ","xPath":"/html[1]/body[1]/div[1]/div[2]/div[4]/div[2]/div[1]/div[7]/div[3]","XContent":"/html[1]/body[1]/div[1]/div[2]/div[4]/div[2]/div[1]/div[7]/div[3](+)","AllClassName":"div-table right, ","label":"1"}
{"DoC":"5","FontSize_O":12.0,"FontSize_R":1.0909090909090908,"FontWeight":"700","FontWeight_O":700.0,"FontWeight_R":1.0,"InnerTextLength_O":184.0,"InnerTextLength_R":0.06068601583113457,"ImgNum_O":0.0,"ImgNum_R":0.0,"ImgSize":0.0,"IsImg":"false","LinkNum_O":10.0,"LinkNum_R":0.12195121951219512,"LinkTextLength_O":0.25295109612141653,"LinkTextLength_R":0.25295109612141653,"InteractionNum_O":0.0,"InteractionNum_R":0.0,"InteractionSize_O":0.0,"InteractionSize_R":0.0,"FormNum_O":10.0,"FormNum_R":0.12195121951219512,"FormSize_O":1.0909090909090908,"FormSize_R":1.0909090909090908,"OptionNum_O":0.0,"OptionNum_R":0.0,"OptionTextLength_O":0.0,"OptionTextLength_R":0.0,"TableNum_O":0.0,"TableNum_R":0.0,"ParaNum_O":0.0,"ParaNum_R":0.0,"InnerHtmlLength_O":1670.0,"InnerHtmlLength_R":0.008002683534598428,"BlockCenterX":0.5,"BlockCenterY":0.5103890362511052,"BlockRectWidth":1.0,"BlockRectHeight":0.036734693877551024,"ContainTable":"false","TextLen":"184","DOMCldNum":"23","BgColor":"#ffffff","ObjectRectLeft":"0","ObjectRectTop":"1990","ObjectRectWidth":"1420","ObjectRectHeight":"36","ID":"1-9","order":"18","FrameSourceIndex":"0","SourceIndex":"2955","Content":"Tìm kiếm theo từ khóa:  Cho thuê nhà riêng tại Quận 9 Hồ Chí Minh , Cho thuê nhà riêng tại Phường Phú Hữu , Chothuê nhà riêng tại Quận 9 , Cho thuê nhà riêng tại Phường Phú Hữu Quận 9  ","xPath":"/html[1]/body[1]/div[1]/div[2]/div[4]/div[2]/div[1]/div[9]","XContent":"/html[1]/body[1]/div[1]/div[2]/div[4]/div[2]/div[1]/div[9](+)","AllClassName":"tagpanel, ","label":"1"}
{"DoC":"8","FontSize_O":12.0,"FontSize_R":1.0909090909090908,"FontWeight":"normal","FontWeight_O":400.0,"FontWeight_R":0.5714285714285714,"InnerTextLength_O":161.0,"InnerTextLength_R":0.05310026385224274,"ImgNum_O":1.0,"ImgNum_R":0.05,"ImgSize":0.00103435792231972,"IsImg":"false","LinkNum_O":8.0,"LinkNum_R":0.0975609756097561,"LinkTextLength_O":0.10623946037099494,"LinkTextLength_R":0.10623946037099494,"InteractionNum_O":0.0,"InteractionNum_R":0.0,"InteractionSize_O":0.0,"InteractionSize_R":0.0,"FormNum_O":8.0,"FormNum_R":0.0975609756097561,"FormSize_O":1.0909090909090908,"FormSize_R":1.0909090909090908,"OptionNum_O":0.0,"OptionNum_R":0.0,"OptionTextLength_O":0.0,"OptionTextLength_R":0.0,"TableNum_O":0.0,"TableNum_R":0.0,"ParaNum_O":0.0,"ParaNum_R":0.0,"InnerHtmlLength_O":93783.0,"InnerHtmlLength_R":0.4494105807935595,"BlockCenterX":0.5,"BlockCenterY":0.6093059239610963,"BlockRectWidth":1.0,"BlockRectHeight":0.11530612244897959,"ContainTable":"false","TextLen":"161","DOMCldNum":"23","BgColor":"#ffffff","ObjectRectLeft":"0","ObjectRectTop":"2041","ObjectRectWidth":"1420","ObjectRectHeight":"113","ID":"1-10","order":"19","FrameSourceIndex":"0","SourceIndex":"2970","Content":"Mã tin đăng: 2006260667Gói tin rao: Diamond VIPNgày bắt đầu: 26-06-2020Ngày kết thúc: 26-07-2020Nhận các thông tin BĐS phù hợp với yêu cầu của bạn qua emaild  a ","xPath":"/html[1]/body[1]/div[1]/div[2]/div[4]/div[2]/div[1]/div[10]","XContent":"/html[1]/body[1]/div[1]/div[2]/div[4]/div[2]/div[1]/div[10](+)","AllClassName":"post-time, ","label":"1"}
{"DoC":"5","FontSize_O":12.0,"FontSize_R":1.0909090909090908,"FontWeight":"normal","FontWeight_O":400.0,"FontWeight_R":0.5714285714285714,"InnerTextLength_O":139.0,"InnerTextLength_R":0.045844327176781004,"ImgNum_O":0.0,"ImgNum_R":0.0,"ImgSize":0.0,"IsImg":"false","LinkNum_O":18.0,"LinkNum_R":0.21951219512195122,"LinkTextLength_O":0.23440134907251264,"LinkTextLength_R":0.23440134907251264,"InteractionNum_O":0.0,"InteractionNum_R":0.0,"InteractionSize_O":0.0,"InteractionSize_R":0.0,"FormNum_O":18.0,"FormNum_R":0.21951219512195122,"FormSize_O":1.0909090909090908,"FormSize_R":1.0909090909090908,"OptionNum_O":0.0,"OptionNum_R":0.0,"OptionTextLength_O":0.0,"OptionTextLength_R":0.0,"TableNum_O":0.0,"TableNum_R":0.0,"ParaNum_O":0.0,"ParaNum_R":0.0,"InnerHtmlLength_O":1681.0,"InnerHtmlLength_R":0.008055395821353268,"BlockCenterX":0.5,"BlockCenterY":0.7325375773651636,"BlockRectWidth":1.0,"BlockRectHeight":0.04081632653061224,"ContainTable":"false","TextLen":"139","DOMCldNum":"5","BgColor":"#015f95","ObjectRectLeft":"0","ObjectRectTop":"2189","ObjectRectWidth":"1420","ObjectRectHeight":"40","ID":"1-11","order":"20","FrameSourceIndex":"0","SourceIndex":"5403","Content":"GIỚI THIỆUHƯỚNG DẪN SỬ DỤNGQUY ĐỊNHQUY CHẾ HOẠT ĐỘNGBẢO VỆ THÔNG TIN CÁ NHÂNCƠ CHẾ GIẢI QUYẾT TRANH CHẤPLIÊN HỆĐIỀU KHOẢN THỎA THUẬNBÁO GIÁ ","xPath":"/html[1]/body[1]/div[1]/div[2]/div[5]/div[1]","XContent":"/html[1]/body[1]/div[1]/div[2]/div[5]/div[1](+)","AllClassName":"footer-menu, ","label":"0"}
{"DoC":"5","FontSize_O":12.0,"FontSize_R":1.0909090909090908,"FontWeight":"normal","FontWeight_O":400.0,"FontWeight_R":0.5714285714285714,"InnerTextLength_O":1.0,"InnerTextLength_R":3.2981530343007914E-4,"ImgNum_O":2.0,"ImgNum_R":0.1,"ImgSize":0.003723688520350992,"IsImg":"false","LinkNum_O":4.0,"LinkNum_R":0.04878048780487805,"LinkTextLength_O":0.0,"LinkTextLength_R":0.0,"InteractionNum_O":0.0,"InteractionNum_R":0.0,"InteractionSize_O":0.0,"InteractionSize_R":0.0,"FormNum_O":4.0,"FormNum_R":0.04878048780487805,"FormSize_O":1.0909090909090908,"FormSize_R":1.0909090909090908,"OptionNum_O":0.0,"OptionNum_R":0.0,"OptionTextLength_O":0.0,"OptionTextLength_R":0.0,"TableNum_O":0.0,"TableNum_R":0.0,"ParaNum_O":1.0,"ParaNum_R":0.05,"InnerHtmlLength_O":835.0,"InnerHtmlLength_R":0.004001341767299214,"BlockCenterX":0.14084507042253522,"BlockCenterY":0.8828470380194517,"BlockRectWidth":0.28169014084507044,"BlockRectHeight":0.2163265306122449,"ContainTable":"false","TextLen":"1","DOMCldNum":"9","BgColor":"#ffffff","ObjectRectLeft":"0","ObjectRectTop":"2239","ObjectRectWidth":"400","ObjectRectHeight":"212","ID":"1-12-1","order":"21","FrameSourceIndex":"0","SourceIndex":"5464","Content":"  ","xPath":"/html[1]/body[1]/div[1]/div[2]/div[5]/div[2]/div[1]","XContent":"/html[1]/body[1]/div[1]/div[2]/div[5]/div[2]/div[1](+)","AllClassName":"footer-logo, ","label":"0"}
{"DoC":"8","FontSize_O":12.0,"FontSize_R":1.0909090909090908,"FontWeight":"normal","FontWeight_O":400.0,"FontWeight_R":0.5714285714285714,"InnerTextLength_O":571.0,"InnerTextLength_R":0.1883245382585752,"ImgNum_O":0.0,"ImgNum_R":0.0,"ImgSize":0.0,"IsImg":"false","LinkNum_O":12.0,"LinkNum_R":0.14634146341463414,"LinkTextLength_O":0.2057335581787521,"LinkTextLength_R":0.2057335581787521,"InteractionNum_O":0.0,"InteractionNum_R":0.0,"InteractionSize_O":0.0,"InteractionSize_R":0.0,"FormNum_O":12.0,"FormNum_R":0.14634146341463414,"FormSize_O":1.0909090909090908,"FormSize_R":1.0909090909090908,"OptionNum_O":0.0,"OptionNum_R":0.0,"OptionTextLength_O":0.0,"OptionTextLength_R":0.0,"TableNum_O":0.0,"TableNum_R":0.0,"ParaNum_O":9.0,"ParaNum_R":0.45,"InnerHtmlLength_O":2081.0,"InnerHtmlLength_R":0.009972206248801994,"BlockCenterX":0.4735915492957746,"BlockCenterY":0.8828470380194517,"BlockRectWidth":0.3415492957746479,"BlockRectHeight":0.2163265306122449,"ContainTable":"false","TextLen":"571","DOMCldNum":"9","BgColor":"#ffffff","ObjectRectLeft":"430","ObjectRectTop":"2239","ObjectRectWidth":"485","ObjectRectHeight":"212","ID":"1-12-2","order":"22","FrameSourceIndex":"0","SourceIndex":"5475","Content":"CÔNG TY CỔ PHẦN KING DRAGON VIỆT NAMMSDN: 0314932187, đăng ký lần đầu ngày 20/03/2018, đăng ký thay đổi lần 1 ngày15/08/2019Chịu trách nhiệm: Trần Minh Khôi[A] : 142/7 Trường Sa, Phường 15, Quận Bình Thạnh, Thành phố Hồ Chí Minh, ViệtNam[M]: 028. 6276.8206 – Hotline: 0908.888.283[T] : Thứ 2 đến thứ 6: 8h00 - 17h15 | Thứ 7: 8h00 - 12h00- CSKH1 (Miền Nam)  : Zalo: 08888.104.38, Email: cskhmiennam@timnhadat.net.vn- CSKH2 (Miền Trung): Zalo: 08888.941.78, Email: cskhmientrung@timnhadat.net.vn- CSKH3 (Miền Bắc)   : Zalo: 08888.785.38, Email: cskhmienbac@timnhadat.net.vn ","xPath":"/html[1]/body[1]/div[1]/div[2]/div[5]/div[2]/div[2]","XContent":"/html[1]/body[1]/div[1]/div[2]/div[5]/div[2]/div[2](+)","AllClassName":"footer-info, ","label":"0"}
{"DoC":"5","FontSize_O":12.0,"FontSize_R":1.0909090909090908,"FontWeight":"normal","FontWeight_O":400.0,"FontWeight_R":0.5714285714285714,"InnerTextLength_O":60.0,"InnerTextLength_R":0.01978891820580475,"ImgNum_O":1.0,"ImgNum_R":0.05,"ImgSize":0.0028502307192810063,"IsImg":"false","LinkNum_O":2.0,"LinkNum_R":0.024390243902439025,"LinkTextLength_O":0.0,"LinkTextLength_R":0.0,"InteractionNum_O":0.0,"InteractionNum_R":0.0,"InteractionSize_O":0.0,"InteractionSize_R":0.0,"FormNum_O":2.0,"FormNum_R":0.024390243902439025,"FormSize_O":1.0909090909090908,"FormSize_R":1.0909090909090908,"OptionNum_O":0.0,"OptionNum_R":0.0,"OptionTextLength_O":0.0,"OptionTextLength_R":0.0,"TableNum_O":0.0,"TableNum_R":0.0,"ParaNum_O":3.0,"ParaNum_R":0.15,"InnerHtmlLength_O":564.0,"InnerHtmlLength_R":0.002702702702702703,"BlockCenterX":0.825,"BlockCenterY":0.8828470380194517,"BlockRectWidth":0.35,"BlockRectHeight":0.2163265306122449,"ContainTable":"false","TextLen":"60","DOMCldNum":"9","BgColor":"#ffffff","ObjectRectLeft":"923","ObjectRectTop":"2239","ObjectRectWidth":"497","ObjectRectHeight":"212","ID":"1-12-3","order":"23","FrameSourceIndex":"0","SourceIndex":"5567","Content":"Tải ứng dụng di độngCopyright © 2017 - 2020 TIMNHADAT.NET.VN ","xPath":"/html[1]/body[1]/div[1]/div[2]/div[5]/div[2]/div[3]","XContent":"/html[1]/body[1]/div[1]/div[2]/div[5]/div[2]/div[3](+)","AllClassName":"footer-app-info, ","label":"0"}
